iflow_mcp_pdf2md-0.1.0.dist-info/licenses/LICENSE
pdf2md/__init__.py
pdf2md/__main__.py
pdf2md/server.py
iflow_mcp_pdf2md-0.1.0.dist-info/METADATA
iflow_mcp_pdf2md-0.1.0.dist-info/WHEEL
iflow_mcp_pdf2md-0.1.0.dist-info/entry_points.txt
iflow_mcp_pdf2md-0.1.0.dist-info/top_level.txt
iflow_mcp_pdf2md-0.1.0.dist-info/RECORD
