Metadata-Version: 2.4
Name: iflow-mcp_pdf2md
Version: 0.1.0
Summary: PDF to Markdown MCP服务器
Requires-Python: >=3.10
License-File: LICENSE
Requires-Dist: httpx>=0.28.1
Requires-Dist: mcp[cli]>=1.4.1
Requires-Dist: python-dotenv>=1.0.0
Requires-Dist: asyncio>=3.4.3
Requires-Dist: pathlib>=1.0.1
Requires-Dist: typer>=0.9.0
Provides-Extra: dev
Requires-Dist: pytest>=7.0.0; extra == "dev"
Dynamic: license-file
